ops/manifests/__init__.py
ops/manifests/collector.py
ops/manifests/exceptions.py
ops/manifests/manifest.py
ops/manifests/manipulations.py
ops.manifest-1.4.0.dist-info/LICENSE
ops.manifest-1.4.0.dist-info/METADATA
ops.manifest-1.4.0.dist-info/WHEEL
ops.manifest-1.4.0.dist-info/top_level.txt
ops.manifest-1.4.0.dist-info/zip-safe
ops.manifest-1.4.0.dist-info/RECORD
