Metadata-Version: 2.2
Name: ops.manifest
Version: 1.4.0
Summary: Kubernetes manifests for Operators
Author-email: Adam Dyess <adam.dyess@canonical.com>
License: Apache
Project-URL: Repository, https://github.com/canonical/ops-lib-manifest
Project-URL: BugTracker, https://github.com/canonical/ops-lib-manifest/issues
Keywords: juju,charming,kubernetes,operators,manifests,yaml
Classifier: License :: OSI Approved :: Apache Software License
Classifier: Programming Language :: Python
Classifier: Programming Language :: Python :: 3
Classifier: Programming Language :: Python :: 3.8
Classifier: Programming Language :: Python :: 3.9
Classifier: Programming Language :: Python :: 3.10
Classifier: Programming Language :: Python :: 3.11
Classifier: Programming Language :: Python :: 3.12
Requires-Python: >3.8
License-File: LICENSE
Requires-Dist: ops
Requires-Dist: lightkube
